{
  "version": 2,
  "extractor": "papercropper",
  "tables": [
    {
      "url": "assets/tables/openreview/openreview-icml-2025-lioemocq3h/table-001.webp",
      "caption": "",
      "page": 0,
      "index": 1,
      "width": 854,
      "height": 680,
      "label": "Table"
    },
    {
      "url": "assets/tables/openreview/openreview-icml-2025-lioemocq3h/table-002.webp",
      "caption": "",
      "page": 0,
      "index": 2,
      "width": 1420,
      "height": 279,
      "label": "Table"
    },
    {
      "url": "assets/tables/openreview/openreview-icml-2025-lioemocq3h/table-003.webp",
      "caption": "",
      "page": 0,
      "index": 3,
      "width": 1289,
      "height": 420,
      "label": "Table"
    },
    {
      "url": "assets/tables/openreview/openreview-icml-2025-lioemocq3h/table-004.webp",
      "caption": "",
      "page": 0,
      "index": 4,
      "width": 1754,
      "height": 376,
      "label": "Table"
    },
    {
      "url": "assets/tables/openreview/openreview-icml-2025-lioemocq3h/table-005.webp",
      "caption": "",
      "page": 0,
      "index": 5,
      "width": 1763,
      "height": 290,
      "label": "Table"
    },
    {
      "url": "assets/tables/openreview/openreview-icml-2025-lioemocq3h/table-006.webp",
      "caption": "",
      "page": 0,
      "index": 6,
      "width": 1768,
      "height": 355,
      "label": "Table"
    },
    {
      "url": "assets/tables/openreview/openreview-icml-2025-lioemocq3h/table-007.webp",
      "caption": "",
      "page": 0,
      "index": 7,
      "width": 885,
      "height": 299,
      "label": "Table"
    },
    {
      "url": "assets/tables/openreview/openreview-icml-2025-lioemocq3h/table-008.webp",
      "caption": "",
      "page": 0,
      "index": 8,
      "width": 1516,
      "height": 683,
      "label": "Table"
    },
    {
      "url": "assets/tables/openreview/openreview-icml-2025-lioemocq3h/table-009.webp",
      "caption": "",
      "page": 0,
      "index": 9,
      "width": 1763,
      "height": 306,
      "label": "Table"
    },
    {
      "url": "assets/tables/openreview/openreview-icml-2025-lioemocq3h/table-010.webp",
      "caption": "",
      "page": 0,
      "index": 10,
      "width": 1307,
      "height": 376,
      "label": "Table"
    },
    {
      "url": "assets/tables/openreview/openreview-icml-2025-lioemocq3h/table-011.webp",
      "caption": "",
      "page": 0,
      "index": 11,
      "width": 1265,
      "height": 645,
      "label": "Table"
    },
    {
      "url": "assets/tables/openreview/openreview-icml-2025-lioemocq3h/table-012.webp",
      "caption": "",
      "page": 0,
      "index": 12,
      "width": 1767,
      "height": 691,
      "label": "Table"
    },
    {
      "url": "assets/tables/openreview/openreview-icml-2025-lioemocq3h/table-013.webp",
      "caption": "",
      "page": 0,
      "index": 13,
      "width": 1331,
      "height": 575,
      "label": "Table"
    },
    {
      "url": "assets/tables/openreview/openreview-icml-2025-lioemocq3h/table-014.webp",
      "caption": "",
      "page": 0,
      "index": 14,
      "width": 1767,
      "height": 505,
      "label": "Table"
    }
  ]
}